lite_dist2/__init__.py
lite_dist2/common.py
lite_dist2/config.py
lite_dist2/expections.py
lite_dist2/interfaces.py
lite_dist2/py.typed
lite_dist2/type_definitions.py
lite_dist2/curriculum_models/__init__.py
lite_dist2/curriculum_models/curriculum.py
lite_dist2/curriculum_models/mapping.py
lite_dist2/curriculum_models/progress_summary.py
lite_dist2/curriculum_models/study.py
lite_dist2/curriculum_models/study_portables.py
lite_dist2/curriculum_models/study_status.py
lite_dist2/curriculum_models/trial.py
lite_dist2/curriculum_models/trial_table.py
lite_dist2/study_strategies/__init__.py
lite_dist2/study_strategies/all_calculation_study_strategy.py
lite_dist2/study_strategies/base_study_strategy.py
lite_dist2/study_strategies/find_exact_study_strategy.py
lite_dist2/study_strategies/study_strategy_factory.py
lite_dist2/suggest_strategies/__init__.py
lite_dist2/suggest_strategies/base_suggest_strategy.py
lite_dist2/suggest_strategies/sequential_suggest_strategy.py
lite_dist2/table_node_api/__init__.py
lite_dist2/table_node_api/api.py
lite_dist2/table_node_api/start_table_api.py
lite_dist2/table_node_api/table_param.py
lite_dist2/table_node_api/table_response.py
lite_dist2/trial_repositories/__init__.py
lite_dist2/trial_repositories/base_trial_repository.py
lite_dist2/trial_repositories/normal_trial_repository.py
lite_dist2/trial_repositories/trial_repository_factory.py
lite_dist2/trial_repositories/trial_repository_model.py
lite_dist2/value_models/__init__.py
lite_dist2/value_models/aligned_space.py
lite_dist2/value_models/aligned_space_registry.py
lite_dist2/value_models/base_space.py
lite_dist2/value_models/const_param.py
lite_dist2/value_models/jagged_space.py
lite_dist2/value_models/line_segment.py
lite_dist2/value_models/parameter_aligned_space_helper.py
lite_dist2/value_models/point.py
lite_dist2/worker_node/__init__.py
lite_dist2/worker_node/table_node_client.py
lite_dist2/worker_node/trial_runner.py
lite_dist2/worker_node/worker.py
lite_dist2-0.5.0.dist-info/METADATA
lite_dist2-0.5.0.dist-info/WHEEL
lite_dist2-0.5.0.dist-info/entry_points.txt
lite_dist2-0.5.0.dist-info/licenses/LICENSE
lite_dist2-0.5.0.dist-info/RECORD
