Metadata-Version: 2.4
Name: lite-dist2
Version: 0.5.0
Summary: Distributed processing system
Project-URL: Repository, https://github.com/atsuhiron/lite_dist2.git
Author-email: Justica <atsuronreplaced@gmail.com>
License-File: LICENSE
Classifier: Development Status :: 4 - Beta
Classifier: Topic :: System :: Distributed Computing
Requires-Python: >=3.13
Requires-Dist: fastapi>=0.115.11
Requires-Dist: pydantic>=2.10.6
Requires-Dist: requests>=2.32.3
Requires-Dist: tqdm>=4.67.1
Requires-Dist: uvicorn>=0.33.0
